krigeo/__init__.py
krigeo/__version__.py
krigeo/covariance/__init__.py
krigeo/covariance/covariance.py
krigeo/covariance/factory.py
krigeo/covariance/variogram.py
krigeo/covariance/models/__init__.py
krigeo/covariance/models/cubic.py
krigeo/covariance/models/exponential.py
krigeo/covariance/models/gaussian.py
krigeo/covariance/models/spherical.py
krigeo/drifts/__init__.py
krigeo/drifts/drift.py
krigeo/drifts/factory.py
krigeo/drifts/fault.py
krigeo/drifts/network.py
krigeo/drifts/drift_models/__init__.py
krigeo/drifts/drift_models/gaussian.py
krigeo/drifts/drift_models/heaviside.py
krigeo/drifts/drift_models/linear.py
krigeo/drifts/fault_models/__init__.py
krigeo/drifts/fault_models/vertical.py
krigeo/kriging/__init__.py
krigeo/kriging/dual.py
krigeo/kriging/ordinary.py
krigeo/kriging/simple.py
krigeo/kriging/universal.py
krigeo-0.2.1.dist-info/licenses/LICENSE
krigeo-0.2.1.dist-info/METADATA
krigeo-0.2.1.dist-info/WHEEL
krigeo-0.2.1.dist-info/top_level.txt
krigeo-0.2.1.dist-info/RECORD
