Metadata-Version: 2.4
Name: krigeo
Version: 0.2.1
Summary: a versatile python kriging tool.
Author-email: Lois LETELLIER <l.letellier@brgm.fr>, Simon LOPEZ <s.lopez@brgm.fr>, Thomas JANVIER <t.janvier@brgm.fr>
Maintainer-email: Thomas JANVIER <t.janvier@brgm.fr>
License:                     GNU AFFERO GENERAL PUBLIC LICENSE
Project-URL: homepage, https://gitlab.com/brgm/geomodelling/spatial/krigeo
Project-URL: repository, https://gitlab.com/brgm/geomodelling/spatial/krigeo
Classifier: Programming Language :: Python :: 3
Classifier: License :: OSI Approved :: GNU Affero General Public License v3
Classifier: Topic :: Scientific/Engineering
Requires-Python: >=3
License-File: LICENSE
Requires-Dist: numpy
Requires-Dist: scipy
Provides-Extra: test
Requires-Dist: pytest; extra == "test"
Provides-Extra: compare
Requires-Dist: pytest; extra == "compare"
Requires-Dist: pykrige; extra == "compare"
Requires-Dist: gstools; extra == "compare"
Dynamic: license-file
